donttrust/__init__.py
donttrust/exceptions.py
donttrust/schema.py
donttrust-0.1.4.dist-info/LICENSE
donttrust-0.1.4.dist-info/METADATA
donttrust-0.1.4.dist-info/WHEEL
donttrust-0.1.4.dist-info/top_level.txt
donttrust-0.1.4.dist-info/RECORD
