Metadata-Version: 2.1
Name: donttrust
Version: 0.1.4
Summary: Form validation library for python
Home-page: https://github.com/arnu515/donttrust
Author: arnu515
Author-email: arnu5152@gmail.com
License: MIT
Keywords: form validation trust joi
Platform: UNKNOWN
Classifier: Development Status :: 4 - Beta
Classifier: Intended Audience :: Developers
Classifier: License :: OSI Approved :: MIT License
Classifier: Natural Language :: English
Classifier: Operating System :: OS Independent
Classifier: Programming Language :: Python :: 3
Classifier: Programming Language :: Python :: 3 :: Only
Classifier: Typing :: Typed
